setupdoc/__init__.py
setupdoc/__main__.py
setupdoc/generators.py
setupdoc/ui.py
setupdoc-1.0.0.dist-info/METADATA
setupdoc-1.0.0.dist-info/WHEEL
setupdoc-1.0.0.dist-info/entry_points.txt
setupdoc-1.0.0.dist-info/top_level.txt
setupdoc-1.0.0.dist-info/RECORD
