Metadata-Version: 2.1
Name: setupdoc
Version: 1.0.0
Summary: UNKNOWN
Home-page: UNKNOWN
Author: Elia Toselli
Author-email: elia.toselli@outlook.it
License: UNKNOWN
Platform: UNKNOWN
Requires-Dist: setuptools
